agno/__init__.py
agno/constants.py
agno/py.typed
agno/aws/__init__.py
agno/aws/api_client.py
agno/aws/context.py
agno/aws/resources.py
agno/aws/app/__init__.py
agno/aws/app/base.py
agno/aws/app/celery/__init__.py
agno/aws/app/celery/worker.py
agno/aws/app/django/__init__.py
agno/aws/app/django/django.py
agno/aws/app/fastapi/__init__.py
agno/aws/app/fastapi/fastapi.py
agno/aws/app/streamlit/__init__.py
agno/aws/app/streamlit/streamlit.py
agno/aws/resource/__init__.py
agno/aws/resource/base.py
agno/aws/resource/reference.py
agno/aws/resource/types.py
agno/aws/resource/acm/__init__.py
agno/aws/resource/acm/certificate.py
agno/aws/resource/cloudformation/__init__.py
agno/aws/resource/cloudformation/stack.py
agno/aws/resource/ec2/__init__.py
agno/aws/resource/ec2/security_group.py
agno/aws/resource/ec2/subnet.py
agno/aws/resource/ec2/volume.py
agno/aws/resource/ecs/__init__.py
agno/aws/resource/ecs/cluster.py
agno/aws/resource/ecs/container.py
agno/aws/resource/ecs/service.py
agno/aws/resource/ecs/task_definition.py
agno/aws/resource/ecs/volume.py
agno/aws/resource/elasticache/__init__.py
agno/aws/resource/elasticache/cluster.py
agno/aws/resource/elasticache/subnet_group.py
agno/aws/resource/elb/__init__.py
agno/aws/resource/elb/listener.py
agno/aws/resource/elb/load_balancer.py
agno/aws/resource/elb/target_group.py
agno/aws/resource/emr/__init__.py
agno/aws/resource/emr/cluster.py
agno/aws/resource/glue/__init__.py
agno/aws/resource/glue/crawler.py
agno/aws/resource/iam/__init__.py
agno/aws/resource/iam/policy.py
agno/aws/resource/iam/role.py
agno/aws/resource/rds/__init__.py
agno/aws/resource/rds/db_cluster.py
agno/aws/resource/rds/db_instance.py
agno/aws/resource/rds/db_subnet_group.py
agno/aws/resource/s3/__init__.py
agno/aws/resource/s3/bucket.py
agno/aws/resource/s3/object.py
agno/aws/resource/secret/__init__.py
agno/aws/resource/secret/manager.py
agno/aws/resource/secret/reader.py
agno/base/__init__.py
agno/base/app.py
agno/base/base.py
agno/base/context.py
agno_infra-1.0.7.dist-info/licenses/LICENSE
agno_infra-1.0.7.dist-info/METADATA
agno_infra-1.0.7.dist-info/WHEEL
agno_infra-1.0.7.dist-info/entry_points.txt
agno_infra-1.0.7.dist-info/top_level.txt
agno_infra-1.0.7.dist-info/RECORD
